[{"content":"Combing through KDE\u0026rsquo;s sites to check for compliance with WCAG A-level KDE\u0026rsquo;s Main Site Assistive Reader No issues.\nAlternative Text on Images With KDE Eco:\n\u0026lt;img class=\u0026#34;img-fluid\u0026#34; src=\u0026#34;https://kde.org/images/eco_greenerywithlogo_box_500.jpg\u0026#34; alt=\u0026#34;\u0026#34; width=\u0026#34;500\u0026#34; loading=\u0026#34;lazy\u0026#34;\u0026gt; ... \u0026lt;img alt=\u0026#34;BMUV\u0026#34; src=\u0026#34;https://eco.kde.org//assets/img/bmuv.webp\u0026#34;\u0026gt; BMUV is not very descriptive.\nKDE Plasma Assistive Reader No issues.\nAlternative Text on Images All images had alternative text.\nETC No other issues found.\nKrita Assistive Reader No issues.\nAlternative Text on Images \u0026lt;img class=\u0026#34;lazy loaded\u0026#34; src=\u0026#34;https://krita.org/wp-content/themes/krita-org-theme/images/2021-development-fund.png\u0026#34; data-src=\u0026#34;https://krita.org/wp-content/themes/krita-org-theme/images/2021-development-fund.png\u0026#34; style=\u0026#34;max-width: 100%\u0026#34; data-was-processed=\u0026#34;true\u0026#34;\u0026gt; \u0026lt;img class=\u0026#34;lazy loaded\u0026#34; src=\u0026#34;https://krita.org/wp-content/themes/krita-org-theme/images/kde-logo.png\u0026#34; data-src=\u0026#34;https://krita.org/wp-content/themes/krita-org-theme/images/kde-logo.png\u0026#34; height=\u0026#34;50\u0026#34; width=\u0026#34;50\u0026#34; data-was-processed=\u0026#34;true\u0026#34;\u0026gt; \u0026hellip; I found a lot more missing alternative tags on Krita.\nETC No other issues found.\nKdenlive Assistive Reader No issues.\nAlternative Text on Images I found a lot more missing alternative tags on Kdenlive.\nETC Autoplayed content on top - may pose issue.\nKontact Assistive Reader No issues.\nAlternative Text on Images Carousel missing alt.\nETC Timed carousel - may violate.\nKontact Assistive Reader No issues.\nAlternative Text on Images I found a lot more missing alternative tags on Kdevelop.\nETC Text is a little cluttered, could violate A guideline.\nGCompris Assistive Reader No issues.\nAlternative Text on Images Missing alternative tags on header and footer.\nETC Autoplayed content on top - may pose issue.\nKDE Neon Assistive Reader No issues.\nAlternative Text on Images Missing alternative tags.\nETC No issues.\nPlasma Mobile Assistive Reader No issues.\nAlternative Text on Images Missing alternative tags.\nETC No issues.\nKDE Frameworks Assistive Reader No issues.\nAlternative Text on Images Missing alternative tags.\nETC No issues.\nKDE Apps Assistive Reader No issues.\nAlternative Text on Images No issues.\nETC Does not look particularily great on mobile.\nKDE Develop Assistive Reader No issues.\nAlternative Text on Images Missing alternative tags.\nETC No issues.\n","permalink":"http://victoriaemily.github.io/KDE/posts/week2/","summary":"Combing through KDE\u0026rsquo;s sites to check for compliance with WCAG A-level KDE\u0026rsquo;s Main Site Assistive Reader No issues.\nAlternative Text on Images With KDE Eco:\n\u0026lt;img class=\u0026#34;img-fluid\u0026#34; src=\u0026#34;https://kde.org/images/eco_greenerywithlogo_box_500.jpg\u0026#34; alt=\u0026#34;\u0026#34; width=\u0026#34;500\u0026#34; loading=\u0026#34;lazy\u0026#34;\u0026gt; ... \u0026lt;img alt=\u0026#34;BMUV\u0026#34; src=\u0026#34;https://eco.kde.org//assets/img/bmuv.webp\u0026#34;\u0026gt; BMUV is not very descriptive.\nKDE Plasma Assistive Reader No issues.\nAlternative Text on Images All images had alternative text.\nETC No other issues found.\nKrita Assistive Reader No issues.\nAlternative Text on Images \u0026lt;img class=\u0026#34;lazy loaded\u0026#34; src=\u0026#34;https://krita.","title":"Week2"},{"content":"Reading the WCAG \u0026amp; Taking More In-Depth Notes Page 13: Controls, Input If non-text content is a control or accepts user input, then it must have a name to describe its purpose (i.e., sign up for mailing lists, etc) – refer to success criterion 4.1.2 Decoration, Formatting, Invisible: NON text content that’s pure decoration should be formatted so that it can be ignored by assistive technology (likely, do a comb through of existing KDE sites with text-to-speech readers)\nPage 14 Prerecorded Media – an alternative for time-based media is appropriate for both audio and video (XOR)\nPage 16 Content does not restrict view to a solitary orientation – check landscape view on mobile, portrait view as well\nPage 17 Distinguishable – make it easier or users to distinguish content from background\nPage 18 Visual presentation of text and images of text have a contrast ratio of at LEAST 4.5:1 (ties into the motto of distinguishable) Large-scale must be 3:1 Logo/brand name text does NOT have a requirement Resize text: text must be able to be resized up to 200 percent without assistive technology\nPage 20 Large Blocks of Text – foreground and background color should be able to be selected by the user\nPage 23 Keyboard accessibility All content should be keyboard navigable\nPage 36 – may apply? Error Prevention\nFor web pages that cause legal/financial commitments \u0026amp;/OR any user information is used, there must be either:\nReversible Confirmed Data is checked \u0026amp; user is provided an opportunity to correct errors Notes of Success Criteria (could aim to make KDE first Level A, then AA, then AAA) – to MEET A, site must meet all of the level A guidelines or provide an alternative version. A: Time based media – audio or visual XOR, alternatives are provided (or an audio track for the case of prerecorded video-only) A: Captions are provided for all prerecorded audio content (not when media is alt for text \u0026amp; is labeled as such) A: Alternatives (or an audio description) are provided for all prerecorded video only content (not when media is alt for text \u0026amp; is labeled as such) Adaptable Information, structure, and relationships conveyed by presentation can be programmatically determined or vailaible through text Instructions for content does not rely on components such as shape, color, size, visual location, etc Use of Color Color is not used as the only visual means to convey information Audio control – auto played audio has an option to pause, stop, and control audio volume (\u0026gt; 3s) No keyboard trap – all parts can be accessible by keyboard interface (if not using standard arrow or tab keys, user is told of different way to navigate from object of focus) Character key shortcuts – keyboard shortcuts are implemented one of the following MUST be true:\no\tTurn off\no\tRemap\no\tActive only when a certain component has focus Timed Content For all timed content, one must be true:\no\tTurn off\no\tAdjust time limit\no\tExtend – warned 20 s before ends, allowed to extend time For blinking, scrolling, and auto-updating information – ALL true\no\tMoving, blinking, scrolling \u0026amp; auto-updating content: (1) starts automatically, lasts \u0026gt; 5s, parallel with other content, there must be a way for the user to PAUSE STOP or HIDE content OR for AAA .. just have NO timing Seizures Do not design content that will give users seizures DO NOT flash over three times in a 1 s period Pointer Gestures Pointer gestures – all content/functionality using multipoint or path-based gestures can be operated with a single pointer UNLESS essential For such functionality, one MUST be true\no\tNo down-event\no\tAbort or undo\no\tUp reversal\no\tEssential – function for the down-event is REQUIRED User Components \u0026amp; Motion User components with labels of text/images of text – name contains text presented visually ( best practice – text at start of the name) Functionality based on motion may also be triggered by COMPONENTS – thus, no motion required Motion may also be disabled Human Language Default human language may be programmatically determined Focus of Human Components On focus: changing the focus of user components OR changing the setting of any user interface component DOES NOT cause a change of context Errors ERROR – if an error is found, the user is informed of the error in text Labels/instructions are provided when content requires user input Robust – elements have complete tags, nested according to specifications and do not contain duplicate attributes For all user interface components, the role and role may be programmatically determined and programmatically set Bypass blocks of text on web pages An annotated PDF of the WCAG 2.1 guidelines can be found below A-level guidelines are highlighted in YELLOW while interesting lines I read are highlighted in BLUE.\n84-pg PDF of Annotated WCAG Guidelines\nWord Version of Above Blog Post\n","permalink":"http://victoriaemily.github.io/KDE/posts/wcag/","summary":"Reading the WCAG \u0026amp; Taking More In-Depth Notes Page 13: Controls, Input If non-text content is a control or accepts user input, then it must have a name to describe its purpose (i.e., sign up for mailing lists, etc) – refer to success criterion 4.1.2 Decoration, Formatting, Invisible: NON text content that’s pure decoration should be formatted so that it can be ignored by assistive technology (likely, do a comb through of existing KDE sites with text-to-speech readers)","title":"WCAG"},{"content":"Start of SoK Hello! Today (in UTC) marks the official start of Season of KDE! In about two weeks or so, I\u0026rsquo;ll update the site on what I\u0026rsquo;ve learned, but recently, I\u0026rsquo;ve been reading up on web accessibility guidelines according to those latest published by WCAG.\nWCAG During my research, I noted the following that could be applicable to KDE\u0026rsquo;s main sites, with the following in quotes either paraphrased or taken directly from WCAG 2.2 (from what I\u0026rsquo;ve seen so far):\n\u0026ldquo;Non-text content must have alternative text, excluding the following:\ncontrols, input (but use must be clear through text) time based media (films, videos, etc) alternative text must provide a descriptive id of non-text content \u0026hellip; Captions should be provided in media.\u0026rdquo; KDE\u0026rsquo;s main sites has many images that are missing alternative text, and this could definitely be implemented.\n\u0026ldquo;Text must be resized without assistive tech up to 200 percent.\u0026rdquo;\nFor the above, I did not notice a option to resize text on KDE\u0026rsquo;s main sites - could be a potential implementation?\nResponsive Web Design: \u0026ldquo;Content can be presented without loss of information or functionality, and without requiring scrolling in two dimensions for:\nVertical scrolling content at a width equivalent to 320 CSS pixels; Horizontal scrolling content at a height equivalent to 256 CSS pixels.\u0026rdquo;\nFor moving, blinking, scrolling, or auto-updating information, all of the following are true:\n\u0026ldquo;Moving, blinking, scrolling For any moving, blinking or scrolling information that (1) starts automatically, (2) lasts more than five seconds, and (3) is presented in parallel with other content, there is a mechanism for the user to pause, stop, or hide it unless the movement, blinking, or scrolling is part of an activity where it is essential\u0026rdquo;\nFor the above, I noticed that KDE does not have auto-scrolling components on its main sites, so it is likely not to be a worry.\n","permalink":"http://victoriaemily.github.io/KDE/posts/week1/","summary":"Start of SoK Hello! Today (in UTC) marks the official start of Season of KDE! In about two weeks or so, I\u0026rsquo;ll update the site on what I\u0026rsquo;ve learned, but recently, I\u0026rsquo;ve been reading up on web accessibility guidelines according to those latest published by WCAG.\nWCAG During my research, I noted the following that could be applicable to KDE\u0026rsquo;s main sites, with the following in quotes either paraphrased or taken directly from WCAG 2.","title":"Week1"},{"content":"I had never heard of KDE prior to learning about Season of KDE, but I had actually used one of their developed softwares before even knowing it was associated with KDE - Krita. I started this blog in interest of Season of KDE, but I hope to start to contribute to OSS like KDE even outside of SoK. :)\nSetting Up \u0026amp; Learning Hugo KDE uses Hugo to template a lot of their subdomains, so I figured it would be relevant to learn to help improve accessability \u0026amp; overall function across their different sites. I had only used CSS \u0026amp; a little bit of React to help format my sites before this, so I tried my hand at using Hugo for templating this site.\nI (of course) downloaded Hugo, set up a theme, and went on to set some features that the demo site for PaperMod had. I enabled a menu, tagging system (apparently Hugo has a taxonomy system that automatically collects tags from your posts \u0026amp; displays it neatly for you!! with a link to it), and a nifty search system.\nSo, this led to the site you see right now!\nI also set up Gitlab \u0026amp; SSH keys and saw this neat easter egg on invent.kde.org: I\u0026rsquo;ve forked the main Krita.org website on Gitlab \u0026amp; cloned it into my local machine.\nGoals for the Next Few Weeks: get comfortable with Gitlab (contribute small changes through the fork i made) research site acessibility according to WCAG guidelines learn to utilize custom CSS with Hugo ultimately, view site source codes and contribute a potential change ","permalink":"http://victoriaemily.github.io/KDE/posts/hugo--setting-goals/","summary":"I had never heard of KDE prior to learning about Season of KDE, but I had actually used one of their developed softwares before even knowing it was associated with KDE - Krita. I started this blog in interest of Season of KDE, but I hope to start to contribute to OSS like KDE even outside of SoK. :)\nSetting Up \u0026amp; Learning Hugo KDE uses Hugo to template a lot of their subdomains, so I figured it would be relevant to learn to help improve accessability \u0026amp; overall function across their different sites.","title":"Pre Season of KDE - Hugo \u0026 Setting Goals"},{"content":"This is the first test blog post! I have added a comments section \u0026amp; familiarized myself a little with Hugo. Goals for now:\ncreate a comment system using mongo atlas create a mockup of a KDE site create my first detailed post at the end detailing what i\u0026rsquo;ve done today! Thanks for reading this test blog post. :) ","permalink":"http://victoriaemily.github.io/KDE/posts/first/","summary":"This is the first test blog post! I have added a comments section \u0026amp; familiarized myself a little with Hugo. Goals for now:\ncreate a comment system using mongo atlas create a mockup of a KDE site create my first detailed post at the end detailing what i\u0026rsquo;ve done today! Thanks for reading this test blog post. :) ","title":"First!"}]